{
  "timestamp": "2026-03-08T14:51:01.083926+00:00",
  "run_id": "4c70a48066",
  "market_summary": {
    "tickers_scanned": 10,
    "buy_signals": 4,
    "sell_signals": 3,
    "hold_signals": 3
  },
  "signals": [
    {
      "ticker": "ETH",
      "latest_price": 4402.37,
      "indicators": {
        "sma_5": 4273.87,
        "sma_20": 4178.06,
        "rsi": 64.0,
        "volatility": 0.142748,
        "momentum": 0.0945
      },
      "signal": {
        "signal": "STRONG_BUY",
        "score": 2,
        "reasons": [
          "SMA5 > SMA20 (bullish)",
          "+momentum (0.0945)"
        ],
        "confidence": 0.5
      }
    },
    {
      "ticker": "NVDA",
      "latest_price": 2982.75,
      "indicators": {
        "sma_5": 2739.93,
        "sma_20": 2609.86,
        "rsi": 49.97,
        "volatility": 0.08291,
        "momentum": 0.1237
      },
      "signal": {
        "signal": "STRONG_BUY",
        "score": 2,
        "reasons": [
          "SMA5 > SMA20 (bullish)",
          "+momentum (0.1237)"
        ],
        "confidence": 0.5
      }
    },
    {
      "ticker": "TSLA",
      "latest_price": 4287.4,
      "indicators": {
        "sma_5": 4168.8,
        "sma_20": 4111.68,
        "rsi": 48.01,
        "volatility": 0.10551,
        "momentum": 0.0738
      },
      "signal": {
        "signal": "STRONG_BUY",
        "score": 2,
        "reasons": [
          "SMA5 > SMA20 (bullish)",
          "+momentum (0.0738)"
        ],
        "confidence": 0.5
      }
    },
    {
      "ticker": "GOOG",
      "latest_price": 1172.83,
      "indicators": {
        "sma_5": 1121.76,
        "sma_20": 1102.45,
        "rsi": 47.74,
        "volatility": 0.096929,
        "momentum": 0.0999
      },
      "signal": {
        "signal": "STRONG_BUY",
        "score": 2,
        "reasons": [
          "SMA5 > SMA20 (bullish)",
          "+momentum (0.0999)"
        ],
        "confidence": 0.5
      }
    },
    {
      "ticker": "BTC",
      "latest_price": 2335.77,
      "indicators": {
        "sma_5": 2374.38,
        "sma_20": 2342.75,
        "rsi": 54.17,
        "volatility": 0.098848,
        "momentum": -0.0417
      },
      "signal": {
        "signal": "HOLD",
        "score": 0,
        "reasons": [
          "SMA5 > SMA20 (bullish)",
          "-momentum (-0.0417)"
        ],
        "confidence": 0.0
      }
    },
    {
      "ticker": "SOL",
      "latest_price": 4493.51,
      "indicators": {
        "sma_5": 4587.92,
        "sma_20": 4661.53,
        "rsi": 51.98,
        "volatility": 0.09145,
        "momentum": 0.0648
      },
      "signal": {
        "signal": "HOLD",
        "score": 0,
        "reasons": [
          "SMA5 < SMA20 (bearish)",
          "+momentum (0.0648)"
        ],
        "confidence": 0.0
      }
    },
    {
      "ticker": "AMZN",
      "latest_price": 2524.47,
      "indicators": {
        "sma_5": 2804.84,
        "sma_20": 2694.49,
        "rsi": 41.27,
        "volatility": 0.079896,
        "momentum": -0.0819
      },
      "signal": {
        "signal": "HOLD",
        "score": 0,
        "reasons": [
          "SMA5 > SMA20 (bullish)",
          "-momentum (-0.0819)"
        ],
        "confidence": 0.0
      }
    },
    {
      "ticker": "META",
      "latest_price": 3491.34,
      "indicators": {
        "sma_5": 3350.31,
        "sma_20": 3388.56,
        "rsi": 61.47,
        "volatility": 0.099554,
        "momentum": 0.0133
      },
      "signal": {
        "signal": "SELL",
        "score": -1,
        "reasons": [
          "SMA5 < SMA20 (bearish)"
        ],
        "confidence": 0.25
      }
    },
    {
      "ticker": "AAPL",
      "latest_price": 4269.29,
      "indicators": {
        "sma_5": 4493.67,
        "sma_20": 4705.21,
        "rsi": 50.95,
        "volatility": 0.069,
        "momentum": -0.1688
      },
      "signal": {
        "signal": "STRONG_SELL",
        "score": -2,
        "reasons": [
          "SMA5 < SMA20 (bearish)",
          "-momentum (-0.1688)"
        ],
        "confidence": 0.5
      }
    },
    {
      "ticker": "MSFT",
      "latest_price": 1373.51,
      "indicators": {
        "sma_5": 1589.05,
        "sma_20": 1665.73,
        "rsi": 42.29,
        "volatility": 0.099637,
        "momentum": -0.2281
      },
      "signal": {
        "signal": "STRONG_SELL",
        "score": -2,
        "reasons": [
          "SMA5 < SMA20 (bearish)",
          "-momentum (-0.2281)"
        ],
        "confidence": 0.5
      }
    }
  ],
  "delta": {
    "status": "compared",
    "deltas": {
      "ETH": {
        "today_signal": "STRONG_BUY",
        "yesterday_signal": "HOLD",
        "price_change_pct": 26.05,
        "signal_changed": true
      },
      "NVDA": {
        "today_signal": "STRONG_BUY",
        "yesterday_signal": "BUY",
        "price_change_pct": -34.64,
        "signal_changed": true
      },
      "TSLA": {
        "today_signal": "STRONG_BUY",
        "yesterday_signal": "BUY",
        "price_change_pct": 98.06,
        "signal_changed": true
      },
      "GOOG": {
        "today_signal": "STRONG_BUY",
        "yesterday_signal": "STRONG_SELL",
        "price_change_pct": -73.03,
        "signal_changed": true
      },
      "BTC": {
        "today_signal": "HOLD",
        "yesterday_signal": "STRONG_SELL",
        "price_change_pct": -50.01,
        "signal_changed": true
      },
      "SOL": {
        "today_signal": "HOLD",
        "yesterday_signal": "HOLD",
        "price_change_pct": 66.81,
        "signal_changed": false
      },
      "AMZN": {
        "today_signal": "HOLD",
        "yesterday_signal": "STRONG_BUY",
        "price_change_pct": 38.39,
        "signal_changed": true
      },
      "META": {
        "today_signal": "SELL",
        "yesterday_signal": "STRONG_SELL",
        "price_change_pct": -13.43,
        "signal_changed": true
      },
      "AAPL": {
        "today_signal": "STRONG_SELL",
        "yesterday_signal": "SELL",
        "price_change_pct": 671.14,
        "signal_changed": true
      },
      "MSFT": {
        "today_signal": "STRONG_SELL",
        "yesterday_signal": "STRONG_BUY",
        "price_change_pct": -36.3,
        "signal_changed": true
      }
    }
  }
}